[
  {"id": 1, "name": "Oversized Hoodie", "category": "Tops", "price": 39.99},
  {"id": 2, "name": "Baggy Jeans", "category": "Bottoms", "price": 49.99},
  {"id": 3, "name": "White Sneakers", "category": "Footwear", "price": 59.9},
  {"id": 4, "name": "Pearl Necklace", "category": "Accessories", "price": 22},
  {"id": 5, "name": "Chunky Boots", "category": "Footwear", "price": 79.99},
  {"id": 6, "name": "Canvas Tote Bag", "category": "Accessories", "price": 19.9},
  {"id": 7, "name": "Classic T-Shirt", "category": "Tops", "price": 19.99},
  {"id": 8, "name": "Cargo Pants", "category": "Bottoms", "price": 44.5},
  {"id": 9, "name": "Ankle Heels", "category": "Footwear", "price": 69.99},
  {"id": 10, "name": "Leather Belt", "category": "Accessories", "price": 25.99},
  {"id": 11, "name": "High-Waisted Trousers", "category": "Bottoms", "price": 42},
  {"id": 12, "name": "Vintage Blouse", "category": "Tops", "price": 29.5},
  {"id": 13, "name": "Beaded Bracelet", "category": "Accessories", "price": 14.99},
  {"id": 14, "name": "Platform Sandals", "category": "Footwear", "price": 49},
  {"id": 15, "name": "Black Top", "category": "Tops", "price": 24.99},
  {"id": 16, "name": "Loafers", "category": "Footwear", "price": 54.5},
  {"id": 17, "name": "Plaid Skirt", "category": "Bottoms", "price": 27.99},
  {"id": 19, "name": "Knit Sweater", "category": "Tops", "price": 34.9},
  {"id": 21, "name": "Silver Hoop Earrings", "category": "Accessories", "price": 18.5},
  {"id": 22, "name": "Cotton Shorts", "category": "Bottoms", "price": 25},
  {"id": 18, "name": "Minimalist Watch", "category": "Accessories", "price": 39},
  {"id": 20, "name": "Sneakers (Alt White)", "category": "Footwear", "price": 59.9},
  {"id": 23, "name": "Embroidered Cap", "category": "Accessories", "price": 21.5},
  {"id": 24, "name": "Wool Beanie", "category": "Headwear", "price": 15.99},
  {"id": 25, "name": "Baseball Cap", "category": "Headwear", "price": 18.5},
  {"id": 26, "name": "Bucket Hat", "category": "Headwear", "price": 21},
  {"id": 27, "name": "Wide-Brim Hat", "category": "Headwear", "price": 27.99},
  {"id": 28, "name": "Knitted Headband", "category": "Headwear", "price": 12.75}
]
